{"namedChunkGroups":{"polyfill":{"name":"polyfill","assets":[{"name":"webpack-runtime-06cb99aacd950ef92c4a.js","size":4366},{"name":"polyfill-b71bb699a91e59e10992.js","size":82563}],"filteredAssets":0,"assetsSize":86929,"filteredAuxiliaryAssets":0,"auxiliaryAssetsSize":0},"app":{"name":"app","assets":[{"name":"webpack-runtime-06cb99aacd950ef92c4a.js","size":4366},{"name":"framework-a9cd6ae8c924ed42dd54.js","size":128805},{"name":"app-ffe1ed77924ac02cfcce.js","size":90303}],"filteredAssets":0,"assetsSize":223474,"filteredAuxiliaryAssets":0,"auxiliaryAssetsSize":0},"component---src-pages-404-js":{"name":"component---src-pages-404-js","assets":[{"name":"styles.862963d10db560eef4ca.css","size":273826},{"name":"cb1608f2-6c8fe1db4865ac01ade1.js","size":1594},{"name":"commons-e947d669a99ba1923385.js","size":88275},{"name":"component---src-pages-404-js-4b4dc84f0ac9b66b165c.js","size":690}],"filteredAssets":0,"assetsSize":364385,"filteredAuxiliaryAssets":14,"auxiliaryAssetsSize":999948},"component---src-pages-index-js":{"name":"component---src-pages-index-js","assets":[{"name":"styles.862963d10db560eef4ca.css","size":273826},{"name":"cb1608f2-6c8fe1db4865ac01ade1.js","size":1594},{"name":"commons-e947d669a99ba1923385.js","size":88275},{"name":"component---src-pages-index-js-47d875c582c010735860.js","size":9640}],"filteredAssets":0,"assetsSize":373335,"filteredAuxiliaryAssets":14,"auxiliaryAssetsSize":999948}},"assetsByChunkName":{"polyfill":["webpack-runtime-06cb99aacd950ef92c4a.js","polyfill-b71bb699a91e59e10992.js"],"app":["webpack-runtime-06cb99aacd950ef92c4a.js","framework-a9cd6ae8c924ed42dd54.js","app-ffe1ed77924ac02cfcce.js"],"component---src-pages-404-js":["styles.862963d10db560eef4ca.css","cb1608f2-6c8fe1db4865ac01ade1.js","commons-e947d669a99ba1923385.js","component---src-pages-404-js-4b4dc84f0ac9b66b165c.js"],"component---src-pages-index-js":["styles.862963d10db560eef4ca.css","cb1608f2-6c8fe1db4865ac01ade1.js","commons-e947d669a99ba1923385.js","component---src-pages-index-js-47d875c582c010735860.js"]},"childAssetsByChunkName":{}}